certvalidator/__init__.py
certvalidator/_errors.py
certvalidator/_types.py
certvalidator/_version.py
certvalidator/context.py
certvalidator/crl_client.py
certvalidator/errors.py
certvalidator/ocsp_client.py
certvalidator/path.py
certvalidator/registry.py
certvalidator/validate.py
certvalidator-0.11.0.dist-info/DESCRIPTION.rst
certvalidator-0.11.0.dist-info/METADATA
certvalidator-0.11.0.dist-info/RECORD
certvalidator-0.11.0.dist-info/WHEEL
certvalidator-0.11.0.dist-info/metadata.json
certvalidator-0.11.0.dist-info/top_level.txt
